cache_db/__init__.py
cache_db/cache_db.py
emo_cache_db-0.0.3.dist-info/LICENSE
emo_cache_db-0.0.3.dist-info/METADATA
emo_cache_db-0.0.3.dist-info/WHEEL
emo_cache_db-0.0.3.dist-info/top_level.txt
emo_cache_db-0.0.3.dist-info/RECORD
