Metadata-Version: 2.1
Name: emo_cache_db
Version: 0.0.3
Summary: Ön bellek ve json veritabanı işlemlerini yönten modül
Home-page: https://github.com/erenmustafaozdal/cache-db
Author: Eren Mustafa Özdal
Author-email: eren.060737@gmail.com
License: MIT
Requires-Python: >=3.11
License-File: LICENSE
Requires-Dist: emo-file-system
